README.md
pyproject.toml
llmpool/__init__.py
llmpool/pool/__init__.py
llmpool/pool/pool.py
llmpool/pool/ratelimiter.py
ibrahimkirabo_llmpool-0.1.3.dist-info/METADATA
ibrahimkirabo_llmpool-0.1.3.dist-info/WHEEL
ibrahimkirabo_llmpool-0.1.3.dist-info/RECORD
