Metadata-Version: 2.4
Name: ibrahimkirabo-llmpool
Version: 0.1.3
Summary: A package to manage API keys and rate limiting for LLM calls.
Project-URL: Homepage, https://github.com/kiraboibrahim/llmpool
Project-URL: Repository, https://github.com/kiraboibrahim/llmpool
Author-email: Ibrahim Kirabo Ssemmambo <kiraboibra268@gmail.com>
License: MIT License
Requires-Dist: pyrate-limiter
